mldesigner/__init__.py
mldesigner/_component.py
mldesigner/_component_executor.py
mldesigner/_component_generator.py
mldesigner/_component_loader.py
mldesigner/_constants.py
mldesigner/_dependent_component_executor.py
mldesigner/_exceptions.py
mldesigner/_get_io_context.py
mldesigner/_get_root_pipeline_context.py
mldesigner/_input_output.py
mldesigner/_logger_factory.py
mldesigner/_reference_component.py
mldesigner/_utils.py
mldesigner/_version.py
mldesigner/_azure_ai_ml/__init__.py
mldesigner/_cli/__init__.py
mldesigner/_cli/mldesigner_commands.py
mldesigner/_compare/__init__.py
mldesigner/_compare/_compare.py
mldesigner/_compare/_compare_impl.py
mldesigner/_compare/_compare_overrite_generator.py
mldesigner/_compare/_compare_util.py
mldesigner/_compare/_filter_reuse_results.py
mldesigner/_compare/_graph_traversal.py
mldesigner/_compile/__init__.py
mldesigner/_compile/_base_compiler.py
mldesigner/_compile/_compile.py
mldesigner/_compile/_compile_collector.py
mldesigner/_compile/_compile_impl.py
mldesigner/_compile/_component_compiler.py
mldesigner/_compile/_ignore_file.py
mldesigner/_compile/_internal_component_compiler.py
mldesigner/_compile/_pathspec.py
mldesigner/_compile/_pipeline_component_compiler.py
mldesigner/_compile/_promptflow_component_compiler.py
mldesigner/_compile/_utils.py
mldesigner/_execute/__init__.py
mldesigner/_execute/_execute.py
mldesigner/_export/__init__.py
mldesigner/_export/_cycle_validator.py
mldesigner/_export/_export.py
mldesigner/_export/_export_impl.py
mldesigner/_export/_parse_url.py
mldesigner/_generate/__init__.py
mldesigner/_generate/_assets_entity.py
mldesigner/_generate/_assets_schema.py
mldesigner/_generate/_generate_package.py
mldesigner/_generate/_generate_package_impl.py
mldesigner/_generate/_generators/__init__.py
mldesigner/_generate/_generators/_base_component_generator.py
mldesigner/_generate/_generators/_base_generator.py
mldesigner/_generate/_generators/_component_func_generator.py
mldesigner-0.1.0b21.dist-info/METADATA
mldesigner-0.1.0b21.dist-info/WHEEL
mldesigner-0.1.0b21.dist-info/entry_points.txt
mldesigner-0.1.0b21.dist-info/top_level.txt
mldesigner-0.1.0b21.dist-info/RECORD
