Metadata-Version: 2.1
Name: mldesigner
Version: 0.1.0b21
Summary: Azure Machine Learning Designer SDK
Home-page: https://github.com/Azure/azureml-examples/tree/sdk-preview/sdk/jobs/pipelines
Author: Microsoft Corporation
License: MIT License
Keywords: AzureMachineLearning
Classifier: Development Status :: 5 - Production/Stable
Classifier: Intended Audience :: Developers
Classifier: Natural Language :: English
Classifier: Operating System :: OS Independent
Classifier: Programming Language :: Python
Classifier: Programming Language :: Python :: 3.8
Classifier: Programming Language :: Python :: 3.9
Classifier: Programming Language :: Python :: 3.10
Classifier: Programming Language :: Python :: 3.11
Classifier: License :: OSI Approved :: MIT License
Requires-Python: <4.0,>=3.7
Requires-Dist: typing-extensions (<5.0.0)
Requires-Dist: pyyaml (<7.0.0,>=5.1.0)
Requires-Dist: pydash (>=5.1.2)
Provides-Extra: pipeline
Requires-Dist: azure-ai-ml ; extra == 'pipeline'
Requires-Dist: azure-identity ; extra == 'pipeline'
Requires-Dist: jinja2 (<=4.0.0) ; extra == 'pipeline'
Requires-Dist: tqdm (<5.0.0) ; extra == 'pipeline'
Requires-Dist: omegaconf (<3.0,>=2.0.5) ; extra == 'pipeline'
Provides-Extra: promptflow
Requires-Dist: promptflow (>=0.1.0b6) ; extra == 'promptflow'
Requires-Dist: promptflow-tools ; extra == 'promptflow'
